MANIFEST.in
README.md
VERSION
setup.cfg
setup.py
graphbrain/__init__.py
graphbrain/__main__.py
graphbrain/cli.py
graphbrain/constants.py
graphbrain/hyperedge.c
graphbrain/hypergraph.py
graphbrain/logic.py
graphbrain/notebook.py
graphbrain/agents/__init__.py
graphbrain/agents/actors.py
graphbrain/agents/agent.py
graphbrain/agents/claim_actors.py
graphbrain/agents/claims.py
graphbrain/agents/conflicts.py
graphbrain/agents/corefs_dets.py
graphbrain/agents/corefs_names.py
graphbrain/agents/corefs_onto.py
graphbrain/agents/corefs_unidecode.py
graphbrain/agents/csv_parser.py
graphbrain/agents/reddit_parser.py
graphbrain/agents/taxonomy.py
graphbrain/agents/txt_parser.py
graphbrain/commands/__init__.py
graphbrain/commands/create.py
graphbrain/commands/info.py
graphbrain/commands/run.py
graphbrain/data/__init__.py
graphbrain/meaning/__init__.py
graphbrain/meaning/actors.py
graphbrain/meaning/concepts.py
graphbrain/meaning/corefs.py
graphbrain/meaning/lemmas.py
graphbrain/meaning/ontology.py
graphbrain/memory/__init__.py
graphbrain/memory/leveldb.c
graphbrain/memory/permutations.c
graphbrain/parsers/__init__.py
graphbrain/parsers/alpha_beta.c
graphbrain/parsers/nlp.py
graphbrain/parsers/parser.py
graphbrain/parsers/parser_de.c
graphbrain/parsers/parser_en.c
graphbrain/parsers/text.py
graphbrain/stats/__init__.py
graphbrain/stats/hyper_similarity.py
graphbrain/stats/word2vec_similarity.py
graphbrain/tests/__init__.py
graphbrain/tests/test_corefs.py
graphbrain/tests/test_hyperedge.py
graphbrain/tests/test_hypergraph.py
graphbrain/tests/test_logic.py
graphbrain/tests/test_permutations.py
hyperbrain.egg-info/PKG-INFO
hyperbrain.egg-info/SOURCES.txt
hyperbrain.egg-info/dependency_links.txt
hyperbrain.egg-info/entry_points.txt
hyperbrain.egg-info/requires.txt
hyperbrain.egg-info/top_level.txt