Metadata-Version: 2.1
Name: hyperbrain
Version: 0.4.0
Summary: A fork of graphbrain
Home-page: UNKNOWN
Author: Telmo Menezes et al.
Author-email: telmo@telmomenezes.net
License: MIT
Platform: UNKNOWN
Classifier: Development Status :: 4 - Beta
Classifier: Programming Language :: Python :: 3
Classifier: License :: OSI Approved :: MIT License
Classifier: Operating System :: OS Independent
Classifier: Environment :: Console
Classifier: Intended Audience :: Science/Research
Classifier: Topic :: Scientific/Engineering :: Artificial Intelligence
Classifier: Topic :: Scientific/Engineering :: Information Analysis
Classifier: Topic :: Sociology
Requires-Python: >=3.6
Provides-Extra: dev
